lazy_build/progressbar.py
lazy_build/cache.py
lazy_build/color.py
lazy_build/config.py
lazy_build/util.py
lazy_build/main.py
lazy_build/context.py
lazy_build/cli.py
lazy_build/__init__.py
lazy_build-0.3.0.dist-info/entry_points.txt
lazy_build-0.3.0.dist-info/DESCRIPTION.rst
lazy_build-0.3.0.dist-info/metadata.json
lazy_build-0.3.0.dist-info/WHEEL
lazy_build-0.3.0.dist-info/METADATA
lazy_build-0.3.0.dist-info/top_level.txt
lazy_build-0.3.0.dist-info/RECORD
